pylyr/__init__.py
pylyr/crawler.py
pylyr/pylyr.py
pylyr-1.0.2.dist-info/licenses/LICENSE.txt
pylyr-1.0.2.dist-info/METADATA
pylyr-1.0.2.dist-info/WHEEL
pylyr-1.0.2.dist-info/entry_points.txt
pylyr-1.0.2.dist-info/top_level.txt
pylyr-1.0.2.dist-info/RECORD
