Metadata-Version: 2.4
Name: pylyr
Version: 1.0.2
Summary: See song lyrics in the terminal
Author-email: Emmet Weyman <emmetweyman@vt.edu>
License:                     GNU GENERAL PUBLIC LICENSE
Classifier: Programming Language :: Python :: 3
Classifier: Operating System :: POSIX :: Linux
Requires-Python: >=3.11
License-File: LICENSE.txt
Requires-Dist: selenium
Requires-Dist: bs4
Requires-Dist: requests
Requires-Dist: python-mpd2
Requires-Dist: gobject
Requires-Dist: dbus-python
Requires-Dist: pympris
Dynamic: license-file
